PanelAppAPI/PanelApp_tool.py
PanelAppAPI/__init__.py
PanelAppAPI-1.1.dist-info/LICENSE
PanelAppAPI-1.1.dist-info/METADATA
PanelAppAPI-1.1.dist-info/WHEEL
PanelAppAPI-1.1.dist-info/entry_points.txt
PanelAppAPI-1.1.dist-info/top_level.txt
PanelAppAPI-1.1.dist-info/RECORD
