Metadata-Version: 2.1
Name: PanelAppAPI
Version: 1.1
Summary: Python3 client API for PanelApp
Home-page: https://github.com/edg1983/
Author: Edoardo Giacopuzzi
Author-email: edoardo.giacopuzzi@fht.org
License: MIT
Platform: UNKNOWN
Classifier: Development Status :: 5 - Production/Stable
Classifier: Intended Audience :: Science/Research
Classifier: Topic :: Scientific/Engineering :: Bio-Informatics
Classifier: License :: OSI Approved :: MIT License
Classifier: Programming Language :: Python :: 3.7
Classifier: Programming Language :: Python :: 3.8
Classifier: Programming Language :: Python :: 3.9
Classifier: Operating System :: OS Independent
License-File: LICENSE
Requires-Dist: pandas
Requires-Dist: requests
